tap_mongodb/__init__.py
tap_mongodb/config_utils.py
tap_mongodb/db_utils.py
tap_mongodb/errors.py
tap_mongodb/stream_utils.py
tap_mongodb/sync_strategies/change_streams.py
tap_mongodb/sync_strategies/common.py
tap_mongodb/sync_strategies/full_table.py
tap_mongodb/sync_strategies/incremental.py
pipelinewise_tap_mongodb-1.5.0.dist-info/LICENSE
pipelinewise_tap_mongodb-1.5.0.dist-info/METADATA
pipelinewise_tap_mongodb-1.5.0.dist-info/WHEEL
pipelinewise_tap_mongodb-1.5.0.dist-info/entry_points.txt
pipelinewise_tap_mongodb-1.5.0.dist-info/top_level.txt
pipelinewise_tap_mongodb-1.5.0.dist-info/RECORD
