Metadata-Version: 2.1
Name: pipelinewise-tap-mongodb
Version: 1.5.0
Summary: Singer.io tap for extracting data from MongoDB - Pipelinewise compatible
Home-page: https://github.com/transferwise/pipelinewise-tap-mongodb
Author: Wise
Classifier: Programming Language :: Python :: 3 :: Only
Classifier: Programming Language :: Python :: 3.6
Classifier: Programming Language :: Python :: 3.7
Classifier: Programming Language :: Python :: 3.8
License-File: LICENSE
Requires-Dist: pipelinewise-singer-python ==1.*
Requires-Dist: pymongo ==4.7.*
Requires-Dist: tzlocal ==2.1.*
Requires-Dist: terminaltables ==3.1.*
Requires-Dist: dnspython ==2.1.*
Provides-Extra: dev
Requires-Dist: pylint ==2.12 ; extra == 'dev'
Requires-Dist: ipdb ==0.13.* ; extra == 'dev'
Provides-Extra: test
Requires-Dist: pytest ==6.2.5 ; extra == 'test'
Requires-Dist: pytest-cov ==3.0.0 ; extra == 'test'
